{"success":true,"limit_reached":false,"status_code":200,"error_message":null,"csv":null,"symbol":"INBS","annualReports":[{"fiscalDateEnding":"2024-06-30","reportedCurrency":"USD","operatingCashflow":"-9571569","paymentsForOperatingActivities":"None","proceedsFromOperatingActivities":"None","changeInOperatingLiabilities":"-945712","changeInOperatingAssets":"-121746","depreciationDepletionAndAmortization":"974355","capitalExpenditures":"5368","changeInReceivables":"135843","changeInInventory":"-202370","profitLoss":"-10190932","cashflowFromInvestment":"-221426","cashflowFromFinancing":"14560556","proceedsFromRepaymentsOfShortTermDebt":"None","paymentsForRepurchaseOfCommonStock":"None","paymentsForRepurchaseOfEquity":"None","paymentsForRepurchaseOfPreferredStock":"None","dividendPayout":"None","dividendPayoutCommonStock":"None","dividendPayoutPreferredStock":"None","proceedsFromIssuanceOfCommonStock":"None","proceedsFromIssuanceOfLongTermDebtAndCapitalSecuritiesNet":"None","proceedsFromIssuanceOfPreferredStock":"None","proceedsFromRepurchaseOfEquity":"10774392","proceedsFromSaleOfTreasuryStock":"None","changeInCashAndCashEquivalents":"None","changeInExchangeRate":"None","netIncome":"-10156759"},{"fiscalDateEnding":"2023-06-30","reportedCurrency":"USD","operatingCashflow":"-7377378","paymentsForOperatingActivities":"None","proceedsFromOperatingActivities":"None","changeInOperatingLiabilities":"-49144","changeInOperatingAssets":"757586","depreciationDepletionAndAmortization":"814481","capitalExpenditures":"505123","changeInReceivables":"293861","changeInInventory":"345390","profitLoss":"-10664555","cashflowFromInvestment":"-694142","cashflowFromFinancing":"1435323","proceedsFromRepaymentsOfShortTermDebt":"None","paymentsForRepurchaseOfCommonStock":"None","paymentsForRepurchaseOfEquity":"None","paymentsForRepurchaseOfPreferredStock":"None","dividendPayout":"None","dividendPayoutCommonStock":"None","dividendPayoutPreferredStock":"None","proceedsFromIssuanceOfCommonStock":"None","proceedsFromIssuanceOfLongTermDebtAndCapitalSecuritiesNet":"None","proceedsFromIssuanceOfPreferredStock":"220578","proceedsFromRepurchaseOfEquity":"220578","proceedsFromSaleOfTreasuryStock":"None","changeInCashAndCashEquivalents":"None","changeInExchangeRate":"None","netIncome":"-10631720"},{"fiscalDateEnding":"2022-06-30","reportedCurrency":"USD","operatingCashflow":"-3358034","paymentsForOperatingActivities":"None","proceedsFromOperatingActivities":"None","changeInOperatingLiabilities":"271511","changeInOperatingAssets":"-1495148","depreciationDepletionAndAmortization":"0","capitalExpenditures":"380221","changeInReceivables":"-1828891","changeInInventory":"-345390","profitLoss":"-8333976","cashflowFromInvestment":"-880221","cashflowFromFinancing":"1435323","proceedsFromRepaymentsOfShortTermDebt":"None","paymentsForRepurchaseOfCommonStock":"None","paymentsForRepurchaseOfEquity":"None","paymentsForRepurchaseOfPreferredStock":"None","dividendPayout":"None","dividendPayoutCommonStock":"None","dividendPayoutPreferredStock":"None","proceedsFromIssuanceOfCommonStock":"None","proceedsFromIssuanceOfLongTermDebtAndCapitalSecuritiesNet":"None","proceedsFromIssuanceOfPreferredStock":"None","proceedsFromRepurchaseOfEquity":"None","proceedsFromSaleOfTreasuryStock":"None","changeInCashAndCashEquivalents":"None","changeInExchangeRate":"None","netIncome":"-8306051"},{"fiscalDateEnding":"2021-06-30","reportedCurrency":"USD","operatingCashflow":"-11296477","paymentsForOperatingActivities":"185301","proceedsFromOperatingActivities":"None","changeInOperatingLiabilities":"-951226","changeInOperatingAssets":"2963955","depreciationDepletionAndAmortization":"966732","capitalExpenditures":"380221","changeInReceivables":"None","changeInInventory":"1025455","profitLoss":"-7060201","cashflowFromInvestment":"-880221","cashflowFromFinancing":"23402918","proceedsFromRepaymentsOfShortTermDebt":"None","paymentsForRepurchaseOfCommonStock":"None","paymentsForRepurchaseOfEquity":"2003952","paymentsForRepurchaseOfPreferredStock":"None","dividendPayout":"None","dividendPayoutCommonStock":"None","dividendPayoutPreferredStock":"None","proceedsFromIssuanceOfCommonStock":"508300","proceedsFromIssuanceOfLongTermDebtAndCapitalSecuritiesNet":"None","proceedsFromIssuanceOfPreferredStock":"3812","proceedsFromRepurchaseOfEquity":"22894618","proceedsFromSaleOfTreasuryStock":"None","changeInCashAndCashEquivalents":"12106441","changeInExchangeRate":"None","netIncome":"-7037286"}],"quarterlyReports":[{"fiscalDateEnding":"2024-09-30","reportedCurrency":"USD","operatingCashflow":"-2387216","paymentsForOperatingActivities":"None","proceedsFromOperatingActivities":"None","changeInOperatingLiabilities":"180969","changeInOperatingAssets":"136333","depreciationDepletionAndAmortization":"241622","capitalExpenditures":"None","changeInReceivables":"148874","changeInInventory":"-38748","profitLoss":"-2694799","cashflowFromInvestment":"None","cashflowFromFinancing":"42450","proceedsFromRepaymentsOfShortTermDebt":"None","paymentsForRepurchaseOfCommonStock":"None","paymentsForRepurchaseOfEquity":"None","paymentsForRepurchaseOfPreferredStock":"None","dividendPayout":"None","dividendPayoutCommonStock":"None","dividendPayoutPreferredStock":"None","proceedsFromIssuanceOfCommonStock":"34511","proceedsFromIssuanceOfLongTermDebtAndCapitalSecuritiesNet":"None","proceedsFromIssuanceOfPreferredStock":"None","proceedsFromRepurchaseOfEquity":"42450","proceedsFromSaleOfTreasuryStock":"None","changeInCashAndCashEquivalents":"None","changeInExchangeRate":"None","netIncome":"-2685633"},{"fiscalDateEnding":"2024-06-30","reportedCurrency":"USD","operatingCashflow":"-2944014","paymentsForOperatingActivities":"None","proceedsFromOperatingActivities":"None","changeInOperatingLiabilities":"-304743","changeInOperatingAssets":"-85784","depreciationDepletionAndAmortization":"236449","capitalExpenditures":"167308","changeInReceivables":"69803","changeInInventory":"-100368","profitLoss":"-2795360","cashflowFromInvestment":"-167308","cashflowFromFinancing":"5313","proceedsFromRepaymentsOfShortTermDebt":"None","paymentsForRepurchaseOfCommonStock":"None","paymentsForRepurchaseOfEquity":"None","paymentsForRepurchaseOfPreferredStock":"None","dividendPayout":"None","dividendPayoutCommonStock":"None","dividendPayoutPreferredStock":"None","proceedsFromIssuanceOfCommonStock":"None","proceedsFromIssuanceOfLongTermDebtAndCapitalSecuritiesNet":"None","proceedsFromIssuanceOfPreferredStock":"None","proceedsFromRepurchaseOfEquity":"5313","proceedsFromSaleOfTreasuryStock":"None","changeInCashAndCashEquivalents":"None","changeInExchangeRate":"None","netIncome":"-2784247"},{"fiscalDateEnding":"2024-03-31","reportedCurrency":"USD","operatingCashflow":"-2446564","paymentsForOperatingActivities":"None","proceedsFromOperatingActivities":"None","changeInOperatingLiabilities":"84661","changeInOperatingAssets":"185096","depreciationDepletionAndAmortization":"258862","capitalExpenditures":"2415.7","changeInReceivables":"97067","changeInInventory":"-133161","profitLoss":"-2986765","cashflowFromInvestment":"2551","cashflowFromFinancing":"10769079","proceedsFromRepaymentsOfShortTermDebt":"None","paymentsForRepurchaseOfCommonStock":"None","paymentsForRepurchaseOfEquity":"None","paymentsForRepurchaseOfPreferredStock":"None","dividendPayout":"None","dividendPayoutCommonStock":"None","dividendPayoutPreferredStock":"None","proceedsFromIssuanceOfCommonStock":"None","proceedsFromIssuanceOfLongTermDebtAndCapitalSecuritiesNet":"None","proceedsFromIssuanceOfPreferredStock":"None","proceedsFromRepurchaseOfEquity":"7732856","proceedsFromSaleOfTreasuryStock":"None","changeInCashAndCashEquivalents":"None","changeInExchangeRate":"None","netIncome":"-2977667"},{"fiscalDateEnding":"2023-12-31","reportedCurrency":"USD","operatingCashflow":"-2869158","paymentsForOperatingActivities":"None","proceedsFromOperatingActivities":"None","changeInOperatingLiabilities":"-1876254","changeInOperatingAssets":"-408256","depreciationDepletionAndAmortization":"231446","capitalExpenditures":"56669","changeInReceivables":"-304676","changeInInventory":"-21876","profitLoss":"-1976383","cashflowFromInvestment":"None","cashflowFromFinancing":"3790969","proceedsFromRepaymentsOfShortTermDebt":"None","paymentsForRepurchaseOfCommonStock":"None","paymentsForRepurchaseOfEquity":"None","paymentsForRepurchaseOfPreferredStock":"None","dividendPayout":"None","dividendPayoutCommonStock":"None","dividendPayoutPreferredStock":"None","proceedsFromIssuanceOfCommonStock":"None","proceedsFromIssuanceOfLongTermDebtAndCapitalSecuritiesNet":"None","proceedsFromIssuanceOfPreferredStock":"None","proceedsFromRepurchaseOfEquity":"None","proceedsFromSaleOfTreasuryStock":"None","changeInCashAndCashEquivalents":"None","changeInExchangeRate":"None","netIncome":"-1969641"},{"fiscalDateEnding":"2023-09-30","reportedCurrency":"USD","operatingCashflow":"-1311833","paymentsForOperatingActivities":"None","proceedsFromOperatingActivities":"None","changeInOperatingLiabilities":"1150624","changeInOperatingAssets":"187198","depreciationDepletionAndAmortization":"247598","capitalExpenditures":"None","changeInReceivables":"273649","changeInInventory":"53035","profitLoss":"-2432424","cashflowFromInvestment":"None","cashflowFromFinancing":"None","proceedsFromRepaymentsOfShortTermDebt":"None","paymentsForRepurchaseOfCommonStock":"None","paymentsForRepurchaseOfEquity":"None","paymentsForRepurchaseOfPreferredStock":"None","dividendPayout":"None","dividendPayoutCommonStock":"None","dividendPayoutPreferredStock":"None","proceedsFromIssuanceOfCommonStock":"0","proceedsFromIssuanceOfLongTermDebtAndCapitalSecuritiesNet":"None","proceedsFromIssuanceOfPreferredStock":"None","proceedsFromRepurchaseOfEquity":"None","proceedsFromSaleOfTreasuryStock":"None","changeInCashAndCashEquivalents":"None","changeInExchangeRate":"None","netIncome":"-2425204"},{"fiscalDateEnding":"2023-06-30","reportedCurrency":"USD","operatingCashflow":"-584338","paymentsForOperatingActivities":"None","proceedsFromOperatingActivities":"None","changeInOperatingLiabilities":"914503","changeInOperatingAssets":"199398","depreciationDepletionAndAmortization":"111994","capitalExpenditures":"505123","changeInReceivables":"-2188","changeInInventory":"270524","profitLoss":"-2671389","cashflowFromInvestment":"-181750","cashflowFromFinancing":"46110","proceedsFromRepaymentsOfShortTermDebt":"None","paymentsForRepurchaseOfCommonStock":"None","paymentsForRepurchaseOfEquity":"None","paymentsForRepurchaseOfPreferredStock":"None","dividendPayout":"None","dividendPayoutCommonStock":"None","dividendPayoutPreferredStock":"None","proceedsFromIssuanceOfCommonStock":"0","proceedsFromIssuanceOfLongTermDebtAndCapitalSecuritiesNet":"None","proceedsFromIssuanceOfPreferredStock":"None","proceedsFromRepurchaseOfEquity":"None","proceedsFromSaleOfTreasuryStock":"None","changeInCashAndCashEquivalents":"None","changeInExchangeRate":"None","netIncome":"-2658921"},{"fiscalDateEnding":"2023-03-31","reportedCurrency":"USD","operatingCashflow":"-2518455","paymentsForOperatingActivities":"None","proceedsFromOperatingActivities":"None","changeInOperatingLiabilities":"301086","changeInOperatingAssets":"308851","depreciationDepletionAndAmortization":"352954","capitalExpenditures":"678","changeInReceivables":"-5186","changeInInventory":"39721","profitLoss":"-6352017","cashflowFromInvestment":"173803","cashflowFromFinancing":"1717627","proceedsFromRepaymentsOfShortTermDebt":"None","paymentsForRepurchaseOfCommonStock":"None","paymentsForRepurchaseOfEquity":"None","paymentsForRepurchaseOfPreferredStock":"None","dividendPayout":"None","dividendPayoutCommonStock":"None","dividendPayoutPreferredStock":"None","proceedsFromIssuanceOfCommonStock":"0","proceedsFromIssuanceOfLongTermDebtAndCapitalSecuritiesNet":"None","proceedsFromIssuanceOfPreferredStock":"None","proceedsFromRepurchaseOfEquity":"None","proceedsFromSaleOfTreasuryStock":"None","changeInCashAndCashEquivalents":"None","changeInExchangeRate":"None","netIncome":"-6343906"},{"fiscalDateEnding":"2022-12-31","reportedCurrency":"USD","operatingCashflow":"-2380850","paymentsForOperatingActivities":"None","proceedsFromOperatingActivities":"None","changeInOperatingLiabilities":"-1221599","changeInOperatingAssets":"189565","depreciationDepletionAndAmortization":"388645","capitalExpenditures":"203013","changeInReceivables":"448567","changeInInventory":"255152","profitLoss":"-427071","cashflowFromInvestment":"-211304","cashflowFromFinancing":"-328414","proceedsFromRepaymentsOfShortTermDebt":"None","paymentsForRepurchaseOfCommonStock":"None","paymentsForRepurchaseOfEquity":"None","paymentsForRepurchaseOfPreferredStock":"None","dividendPayout":"8242","dividendPayoutCommonStock":"8242","dividendPayoutPreferredStock":"None","proceedsFromIssuanceOfCommonStock":"0","proceedsFromIssuanceOfLongTermDebtAndCapitalSecuritiesNet":"None","proceedsFromIssuanceOfPreferredStock":"None","proceedsFromRepurchaseOfEquity":"-14407","proceedsFromSaleOfTreasuryStock":"None","changeInCashAndCashEquivalents":"None","changeInExchangeRate":"None","netIncome":"-420600"},{"fiscalDateEnding":"2022-09-30","reportedCurrency":"USD","operatingCashflow":"-1893735","paymentsForOperatingActivities":"None","proceedsFromOperatingActivities":"None","changeInOperatingLiabilities":"-43134","changeInOperatingAssets":"59772","depreciationDepletionAndAmortization":"-39112","capitalExpenditures":"474891","changeInReceivables":"-147332","changeInInventory":"71480","profitLoss":"-1214078","cashflowFromInvestment":"-474891","cashflowFromFinancing":"-328414","proceedsFromRepaymentsOfShortTermDebt":"None","paymentsForRepurchaseOfCommonStock":"None","paymentsForRepurchaseOfEquity":"None","paymentsForRepurchaseOfPreferredStock":"None","dividendPayout":"None","dividendPayoutCommonStock":"None","dividendPayoutPreferredStock":"None","proceedsFromIssuanceOfCommonStock":"0","proceedsFromIssuanceOfLongTermDebtAndCapitalSecuritiesNet":"None","proceedsFromIssuanceOfPreferredStock":"None","proceedsFromRepurchaseOfEquity":"None","proceedsFromSaleOfTreasuryStock":"None","changeInCashAndCashEquivalents":"None","changeInExchangeRate":"None","netIncome":"-1208293"},{"fiscalDateEnding":"2022-06-30","reportedCurrency":"USD","operatingCashflow":"-1723205","paymentsForOperatingActivities":"None","proceedsFromOperatingActivities":"None","changeInOperatingLiabilities":"784951","changeInOperatingAssets":"480597","depreciationDepletionAndAmortization":"0","capitalExpenditures":"203013","changeInReceivables":"0","changeInInventory":"None","profitLoss":"-2088180","cashflowFromInvestment":"-703013","cashflowFromFinancing":"None","proceedsFromRepaymentsOfShortTermDebt":"None","paymentsForRepurchaseOfCommonStock":"None","paymentsForRepurchaseOfEquity":"None","paymentsForRepurchaseOfPreferredStock":"None","dividendPayout":"None","dividendPayoutCommonStock":"None","dividendPayoutPreferredStock":"None","proceedsFromIssuanceOfCommonStock":"0","proceedsFromIssuanceOfLongTermDebtAndCapitalSecuritiesNet":"None","proceedsFromIssuanceOfPreferredStock":"None","proceedsFromRepurchaseOfEquity":"None","proceedsFromSaleOfTreasuryStock":"None","changeInCashAndCashEquivalents":"None","changeInExchangeRate":"None","netIncome":"-2078155"},{"fiscalDateEnding":"2022-03-31","reportedCurrency":"USD","operatingCashflow":"-292224","paymentsForOperatingActivities":"None","proceedsFromOperatingActivities":"None","changeInOperatingLiabilities":"473755","changeInOperatingAssets":"118006","depreciationDepletionAndAmortization":"0","capitalExpenditures":"177208","changeInReceivables":"0","changeInInventory":"None","profitLoss":"-1344133","cashflowFromInvestment":"-177208","cashflowFromFinancing":"None","proceedsFromRepaymentsOfShortTermDebt":"None","paymentsForRepurchaseOfCommonStock":"None","paymentsForRepurchaseOfEquity":"None","paymentsForRepurchaseOfPreferredStock":"None","dividendPayout":"None","dividendPayoutCommonStock":"None","dividendPayoutPreferredStock":"None","proceedsFromIssuanceOfCommonStock":"0","proceedsFromIssuanceOfLongTermDebtAndCapitalSecuritiesNet":"None","proceedsFromIssuanceOfPreferredStock":"None","proceedsFromRepurchaseOfEquity":"None","proceedsFromSaleOfTreasuryStock":"None","changeInCashAndCashEquivalents":"None","changeInExchangeRate":"None","netIncome":"-1335246"},{"fiscalDateEnding":"2021-12-31","reportedCurrency":"USD","operatingCashflow":"-1425567","paymentsForOperatingActivities":"None","proceedsFromOperatingActivities":"None","changeInOperatingLiabilities":"-415606","changeInOperatingAssets":"-24614","depreciationDepletionAndAmortization":"None","capitalExpenditures":"177208","changeInReceivables":"0","changeInInventory":"None","profitLoss":"-3463823","cashflowFromInvestment":"-177208","cashflowFromFinancing":"None","proceedsFromRepaymentsOfShortTermDebt":"None","paymentsForRepurchaseOfCommonStock":"None","paymentsForRepurchaseOfEquity":"None","paymentsForRepurchaseOfPreferredStock":"None","dividendPayout":"None","dividendPayoutCommonStock":"None","dividendPayoutPreferredStock":"None","proceedsFromIssuanceOfCommonStock":"0","proceedsFromIssuanceOfLongTermDebtAndCapitalSecuritiesNet":"None","proceedsFromIssuanceOfPreferredStock":"None","proceedsFromRepurchaseOfEquity":"None","proceedsFromSaleOfTreasuryStock":"None","changeInCashAndCashEquivalents":"-3463823","changeInExchangeRate":"None","netIncome":"-3459998"},{"fiscalDateEnding":"2021-09-30","reportedCurrency":"USD","operatingCashflow":"82962","paymentsForOperatingActivities":"None","proceedsFromOperatingActivities":"None","changeInOperatingLiabilities":"-571589","changeInOperatingAssets":"-2069137","depreciationDepletionAndAmortization":"None","capitalExpenditures":"177208","changeInReceivables":"-1828891","changeInInventory":"None","profitLoss":"-1437840","cashflowFromInvestment":"-177208","cashflowFromFinancing":"None","proceedsFromRepaymentsOfShortTermDebt":"None","paymentsForRepurchaseOfCommonStock":"None","paymentsForRepurchaseOfEquity":"None","paymentsForRepurchaseOfPreferredStock":"None","dividendPayout":"None","dividendPayoutCommonStock":"None","dividendPayoutPreferredStock":"None","proceedsFromIssuanceOfCommonStock":"0","proceedsFromIssuanceOfLongTermDebtAndCapitalSecuritiesNet":"None","proceedsFromIssuanceOfPreferredStock":"None","proceedsFromRepurchaseOfEquity":"None","proceedsFromSaleOfTreasuryStock":"None","changeInCashAndCashEquivalents":"82962","changeInExchangeRate":"None","netIncome":"-1432652"},{"fiscalDateEnding":"2021-06-30","reportedCurrency":"USD","operatingCashflow":"-1682811","paymentsForOperatingActivities":"0","proceedsFromOperatingActivities":"None","changeInOperatingLiabilities":"81782","changeInOperatingAssets":"-178039","depreciationDepletionAndAmortization":"None","capitalExpenditures":"None","changeInReceivables":"None","changeInInventory":"None","profitLoss":"-850230","cashflowFromInvestment":"None","cashflowFromFinancing":"0","proceedsFromRepaymentsOfShortTermDebt":"None","paymentsForRepurchaseOfCommonStock":"None","paymentsForRepurchaseOfEquity":"None","paymentsForRepurchaseOfPreferredStock":"None","dividendPayout":"None","dividendPayoutCommonStock":"None","dividendPayoutPreferredStock":"None","proceedsFromIssuanceOfCommonStock":"0","proceedsFromIssuanceOfLongTermDebtAndCapitalSecuritiesNet":"None","proceedsFromIssuanceOfPreferredStock":"None","proceedsFromRepurchaseOfEquity":"None","proceedsFromSaleOfTreasuryStock":"None","changeInCashAndCashEquivalents":"-1682811","changeInExchangeRate":"None","netIncome":"-852999"},{"fiscalDateEnding":"2021-03-31","reportedCurrency":"USD","operatingCashflow":"-6159435","paymentsForOperatingActivities":"18561","proceedsFromOperatingActivities":"None","changeInOperatingLiabilities":"339361","changeInOperatingAssets":"3102508","depreciationDepletionAndAmortization":"None","capitalExpenditures":"None","changeInReceivables":"None","changeInInventory":"None","profitLoss":"-3142667","cashflowFromInvestment":"None","cashflowFromFinancing":"498100","proceedsFromRepaymentsOfShortTermDebt":"None","paymentsForRepurchaseOfCommonStock":"None","paymentsForRepurchaseOfEquity":"None","paymentsForRepurchaseOfPreferredStock":"None","dividendPayout":"None","dividendPayoutCommonStock":"None","dividendPayoutPreferredStock":"None","proceedsFromIssuanceOfCommonStock":"498100","proceedsFromIssuanceOfLongTermDebtAndCapitalSecuritiesNet":"None","proceedsFromIssuanceOfPreferredStock":"None","proceedsFromRepurchaseOfEquity":"None","proceedsFromSaleOfTreasuryStock":"None","changeInCashAndCashEquivalents":"-3142667","changeInExchangeRate":"None","netIncome":"-3127813"},{"fiscalDateEnding":"2020-12-31","reportedCurrency":"USD","operatingCashflow":"-776967","paymentsForOperatingActivities":"None","proceedsFromOperatingActivities":"None","changeInOperatingLiabilities":"None","changeInOperatingAssets":"None","depreciationDepletionAndAmortization":"None","capitalExpenditures":"None","changeInReceivables":"None","changeInInventory":"None","profitLoss":"-1990389","cashflowFromInvestment":"None","cashflowFromFinancing":"19610073","proceedsFromRepaymentsOfShortTermDebt":"None","paymentsForRepurchaseOfCommonStock":"None","paymentsForRepurchaseOfEquity":"None","paymentsForRepurchaseOfPreferredStock":"None","dividendPayout":"None","dividendPayoutCommonStock":"None","dividendPayoutPreferredStock":"None","proceedsFromIssuanceOfCommonStock":"None","proceedsFromIssuanceOfLongTermDebtAndCapitalSecuritiesNet":"None","proceedsFromIssuanceOfPreferredStock":"None","proceedsFromRepurchaseOfEquity":"None","proceedsFromSaleOfTreasuryStock":"None","changeInCashAndCashEquivalents":"-1990389","changeInExchangeRate":"None","netIncome":"-1983964"},{"fiscalDateEnding":"2020-09-30","reportedCurrency":"USD","operatingCashflow":"-2677264","paymentsForOperatingActivities":"None","proceedsFromOperatingActivities":"None","changeInOperatingLiabilities":"None","changeInOperatingAssets":"None","depreciationDepletionAndAmortization":"None","capitalExpenditures":"None","changeInReceivables":"None","changeInInventory":"None","profitLoss":"-1076915","cashflowFromInvestment":"None","cashflowFromFinancing":"3294745","proceedsFromRepaymentsOfShortTermDebt":"None","paymentsForRepurchaseOfCommonStock":"None","paymentsForRepurchaseOfEquity":"None","paymentsForRepurchaseOfPreferredStock":"None","dividendPayout":"None","dividendPayoutCommonStock":"None","dividendPayoutPreferredStock":"None","proceedsFromIssuanceOfCommonStock":"None","proceedsFromIssuanceOfLongTermDebtAndCapitalSecuritiesNet":"None","proceedsFromIssuanceOfPreferredStock":"None","proceedsFromRepurchaseOfEquity":"None","proceedsFromSaleOfTreasuryStock":"None","changeInCashAndCashEquivalents":"None","changeInExchangeRate":"None","netIncome":"-1072510"},{"fiscalDateEnding":"2020-06-30","reportedCurrency":"USD","operatingCashflow":"194975","paymentsForOperatingActivities":"None","proceedsFromOperatingActivities":"None","changeInOperatingLiabilities":"None","changeInOperatingAssets":"None","depreciationDepletionAndAmortization":"None","capitalExpenditures":"None","changeInReceivables":"None","changeInInventory":"None","profitLoss":"-463980","cashflowFromInvestment":"None","cashflowFromFinancing":"201514","proceedsFromRepaymentsOfShortTermDebt":"None","paymentsForRepurchaseOfCommonStock":"None","paymentsForRepurchaseOfEquity":"None","paymentsForRepurchaseOfPreferredStock":"None","dividendPayout":"None","dividendPayoutCommonStock":"None","dividendPayoutPreferredStock":"None","proceedsFromIssuanceOfCommonStock":"None","proceedsFromIssuanceOfLongTermDebtAndCapitalSecuritiesNet":"None","proceedsFromIssuanceOfPreferredStock":"None","proceedsFromRepurchaseOfEquity":"None","proceedsFromSaleOfTreasuryStock":"None","changeInCashAndCashEquivalents":"None","changeInExchangeRate":"None","netIncome":"-1836318"},{"fiscalDateEnding":"2020-03-31","reportedCurrency":"USD","operatingCashflow":"-218651","paymentsForOperatingActivities":"None","proceedsFromOperatingActivities":"None","changeInOperatingLiabilities":"None","changeInOperatingAssets":"None","depreciationDepletionAndAmortization":"None","capitalExpenditures":"None","changeInReceivables":"None","changeInInventory":"None","profitLoss":"-111107","cashflowFromInvestment":"None","cashflowFromFinancing":"648750","proceedsFromRepaymentsOfShortTermDebt":"None","paymentsForRepurchaseOfCommonStock":"None","paymentsForRepurchaseOfEquity":"None","paymentsForRepurchaseOfPreferredStock":"None","dividendPayout":"None","dividendPayoutCommonStock":"None","dividendPayoutPreferredStock":"None","proceedsFromIssuanceOfCommonStock":"None","proceedsFromIssuanceOfLongTermDebtAndCapitalSecuritiesNet":"None","proceedsFromIssuanceOfPreferredStock":"None","proceedsFromRepurchaseOfEquity":"None","proceedsFromSaleOfTreasuryStock":"None","changeInCashAndCashEquivalents":"None","changeInExchangeRate":"None","netIncome":"-112592"},{"fiscalDateEnding":"2019-12-31","reportedCurrency":"USD","operatingCashflow":"5102242","paymentsForOperatingActivities":"None","proceedsFromOperatingActivities":"None","changeInOperatingLiabilities":"None","changeInOperatingAssets":"None","depreciationDepletionAndAmortization":"None","capitalExpenditures":"None","changeInReceivables":"None","changeInInventory":"None","profitLoss":"-1853033","cashflowFromInvestment":"None","cashflowFromFinancing":"-4786560","proceedsFromRepaymentsOfShortTermDebt":"None","paymentsForRepurchaseOfCommonStock":"None","paymentsForRepurchaseOfEquity":"None","paymentsForRepurchaseOfPreferredStock":"None","dividendPayout":"None","dividendPayoutCommonStock":"None","dividendPayoutPreferredStock":"None","proceedsFromIssuanceOfCommonStock":"None","proceedsFromIssuanceOfLongTermDebtAndCapitalSecuritiesNet":"None","proceedsFromIssuanceOfPreferredStock":"None","proceedsFromRepurchaseOfEquity":"None","proceedsFromSaleOfTreasuryStock":"None","changeInCashAndCashEquivalents":"None","changeInExchangeRate":"None","netIncome":"-1836318"},{"fiscalDateEnding":"2019-09-30","reportedCurrency":"USD","operatingCashflow":"-5577184","paymentsForOperatingActivities":"None","proceedsFromOperatingActivities":"None","changeInOperatingLiabilities":"None","changeInOperatingAssets":"None","depreciationDepletionAndAmortization":"None","capitalExpenditures":"None","changeInReceivables":"None","changeInInventory":"None","profitLoss":"-764830","cashflowFromInvestment":"None","cashflowFromFinancing":"5318908","proceedsFromRepaymentsOfShortTermDebt":"None","paymentsForRepurchaseOfCommonStock":"None","paymentsForRepurchaseOfEquity":"None","paymentsForRepurchaseOfPreferredStock":"None","dividendPayout":"None","dividendPayoutCommonStock":"None","dividendPayoutPreferredStock":"None","proceedsFromIssuanceOfCommonStock":"None","proceedsFromIssuanceOfLongTermDebtAndCapitalSecuritiesNet":"None","proceedsFromIssuanceOfPreferredStock":"None","proceedsFromRepurchaseOfEquity":"None","proceedsFromSaleOfTreasuryStock":"None","changeInCashAndCashEquivalents":"None","changeInExchangeRate":"None","netIncome":"-7394377"}]}